{
	"Current ID":"level_2",
	"Next ID":"level_3",
	"Map Format":1,
	"Text":{
		"Dimensions":[
			664,
			38.5
		],
		"Text":"Without obstacles life is pointless.",
		"Color":"808080FE"
	},
	"NormalTerrain":[
		{
			"Scale":[
				24.6907,
				1,
				1
			],
			"Position":[
				-0.06890059,
				-4.75,
				0
			],
			"Name":"NormalTerrain(Clone)",
			"Color":"FFFFFFFE"
		},
		{
			"Scale":[
				0.8888889,
				1.185185,
				1
			],
			"Position":[
				-6.495,
				-4.160418,
				0.0004882813
			],
			"Name":"NormalTerrain(Clone)",
			"Color":"FFFFFFFE"
		},
		{
			"Scale":[
				5.555555,
				0.4561924,
				1
			],
			"Position":[
				-4.408,
				-3.718018,
				0.0004882813
			],
			"Name":"NormalTerrain(Clone)",
			"Color":"FFFFFFFE"
		},
		{
			"Scale":[
				2.296296,
				1.650363,
				1
			],
			"Position":[
				-2.288,
				-4.040418,
				0.0004882813
			],
			"Name":"NormalTerrain(Clone)",
			"Color":"FFFFFFFE"
		},
		{
			"Scale":[
				0.5925926,
				1.412848,
				1
			],
			"Position":[
				-1.32,
				-3.374,
				0.0004882813
			],
			"Name":"NormalTerrain(Clone)",
			"Color":"FFFFFFFE"
		},
		{
			"Scale":[
				1.962963,
				0.953181,
				1
			],
			"Position":[
				-0.6300001,
				-3.249418,
				0.0004882813
			],
			"Name":"NormalTerrain(Clone)",
			"Color":"FFFFFFFE"
		},
		{
			"Scale":[
				0.2962963,
				0.570606,
				1
			],
			"Position":[
				-1.24,
				-4.325718,
				0.0004882813
			],
			"Name":"NormalTerrain(Clone)",
			"Color":"FFFFFFFE"
		},
		{
			"Scale":[
				0.2962963,
				0.2962963,
				1
			],
			"Position":[
				-0.1799998,
				-4.029418,
				0.0004882813
			],
			"Name":"NormalTerrain(Clone)",
			"Color":"FFFFFFFE"
		},
		{
			"Scale":[
				0.2962963,
				0.6666667,
				1
			],
			"Position":[
				2.528,
				-4.302418,
				0.0004882813
			],
			"Name":"NormalTerrain(Clone)",
			"Color":"FFFFFFFE"
		},
		{
			"Scale":[
				0.8888889,
				0.2962963,
				1
			],
			"Position":[
				2.209,
				-4.202518,
				0.0004882813
			],
			"Name":"NormalTerrain(Clone)",
			"Color":"FFFFFFFE"
		},
		{
			"Scale":[
				0.2962963,
				0.2962963,
				1
			],
			"Position":[
				1.619,
				-4.400418,
				0.0004882813
			],
			"Name":"NormalTerrain(Clone)",
			"Color":"FFFFFFFE"
		},
		{
			"Scale":[
				0.2962963,
				0.5828563,
				1
			],
			"Position":[
				0.6110001,
				-4.327,
				0.0004882813
			],
			"Name":"NormalTerrain(Clone)",
			"Color":"FFFFFFFE"
		},
		{
			"Scale":[
				0.2962963,
				0.2962963,
				1
			],
			"Position":[
				0.4510002,
				-4.402418,
				0.0004882813
			],
			"Name":"NormalTerrain(Clone)",
			"Color":"FFFFFFFE"
		}
	],
	"ShadowTerrain":[
		{
			"Scale":[
				5.555555,
				1.185185,
				1
			],
			"Position":[
				-4.408,
				-4.160418,
				0.0004882813
			],
			"Name":"ShadowTerrain(Clone)",
			"Color":"FFFFFFFE"
		},
		{
			"Scale":[
				2.555556,
				2.111111,
				1
			],
			"Position":[
				-0.79,
				-3.916418,
				0.0004882813
			],
			"Name":"ShadowTerrain(Clone)",
			"Color":"FFFFFFFE"
		},
		{
			"Scale":[
				0.8888889,
				0.3703704,
				1
			],
			"Position":[
				2.209,
				-4.380418,
				0.0004882813
			],
			"Name":"ShadowTerrain(Clone)",
			"Color":"FFFFFFFE"
		}
	],
	"Special":[],
	"Objectives":{
		"Blue":{
			"Scale":[
				1,
				1,
				1
			],
			"Position":[
				-3.037089,
				-4.298954,
				-2
			],
			"Name":"BigCubeObjective",
			"Color":"69F0F0F2"
		},
		"Red":{
			"Scale":[
				1,
				1,
				1
			],
			"Position":[
				-1.565089,
				-4.382954,
				-2
			],
			"Name":"SmallCubeObjective",
			"Color":"EA46489E"
		}
	},
	"Spawnpoints":{
		"Red":{
			"Scale":[
				1,
				1,
				1
			],
			"Position":[
				2.343911,
				-4.386954,
				-2
			],
			"Name":"SmallCubeSpawnpoint"
		},
		"Blue":{
			"Scale":[
				1,
				1,
				1
			],
			"Position":[
				-5.574089,
				-3.430954,
				-2
			],
			"Name":"BigCubeSpawnpoint"
		}
	}
}
